aiobtclientapi/__init__.py
aiobtclientapi/cli.py
aiobtclientapi/constants.py
aiobtclientapi/errors.py
aiobtclientapi/response.py
aiobtclientapi/clients/__init__.py
aiobtclientapi/clients/base/__init__.py
aiobtclientapi/clients/base/api.py
aiobtclientapi/clients/deluge/__init__.py
aiobtclientapi/clients/deluge/api.py
aiobtclientapi/clients/qbittorrent/__init__.py
aiobtclientapi/clients/qbittorrent/api.py
aiobtclientapi/clients/rtorrent/__init__.py
aiobtclientapi/clients/rtorrent/api.py
aiobtclientapi/clients/rtorrent/utils.py
aiobtclientapi/clients/transmission/__init__.py
aiobtclientapi/clients/transmission/api.py
aiobtclientapi/clients/transmission/enums.py
aiobtclientapi/utils/__init__.py
aiobtclientapi/utils/monitor.py
aiobtclientapi/utils/torrent.py
docs/conf.py
docs/usage_example.py
tests/errors_test.py
tests/init_test.py
tests/response_test.py
tests/clients_test/base_test/base_api_test.py
tests/clients_test/deluge_test/deluge_api_test.py
tests/clients_test/qbittorrent_test/qbittorrent_api_test.py
tests/clients_test/rtorrent_test/rtorrent_api_test.py
tests/clients_test/rtorrent_test/rtorrent_utils_test.py
tests/clients_test/transmission_test/transmission_api_test.py
tests/utils_test/monitor_test.py
tests/utils_test/torrent_test.py
tests/utils_test/utils_test.py
aiobtclientapi-1.1.3.dist-info/LICENSE
aiobtclientapi-1.1.3.dist-info/METADATA
aiobtclientapi-1.1.3.dist-info/WHEEL
aiobtclientapi-1.1.3.dist-info/entry_points.txt
aiobtclientapi-1.1.3.dist-info/top_level.txt
aiobtclientapi-1.1.3.dist-info/RECORD
